{
  "id": 3,
  "imgUrl": "/images/kimyoungseo/andrew-valdivia-mMI5sdLFoHM-unsplash (2).jpg",
  "title": "콜드 브루",
  "titleName": "돌체 콜드 브루",
  "name": "Dolce Cold Brew",
  "nameContent": "무더운 여름철, 동남아 휴가지에서 즐기는 커피를 떠오르게 하는 스타벅스 음료의 베스트 x 베스트 조합인 돌체 콜드 브루를 만나보세요!",
  "nutrition": [
    { "id": 1, "name": "1회 제공량 (kcal)", "percent": 265 },
    { "id": 2, "name": "포화지방 (g)", "percent": 9 },
    { "id": 3, "name": "단백질 (g)", "percent": 8 },
    { "id": 4, "name": "나트륨 (mg)", "percent": 130 },
    { "id": 5, "name": "당류 (g)", "percent": 29 },
    { "id": 6, "name": "카페인 (mg)", "percent": 150 }
  ],
  "product_fator": "우유"
}
